README.md
setup.cfg
setup.py
capesbusca/__init__.py
capesbusca/request.py
capesbusca/searcherror.py
capesbusca/searchquery.py
capesbusca/searchresult.py
capesbusca.egg-info/PKG-INFO
capesbusca.egg-info/SOURCES.txt
capesbusca.egg-info/dependency_links.txt
capesbusca.egg-info/requires.txt
capesbusca.egg-info/top_level.txt
capesbusca/filters/__init__.py
capesbusca/filters/ano.py
capesbusca/filters/areaavaliacao.py
capesbusca/filters/areaconcentracao.py
capesbusca/filters/areaconhecimento.py
capesbusca/filters/autor.py
capesbusca/filters/banca.py
capesbusca/filters/biblioteca.py
capesbusca/filters/filter.py
capesbusca/filters/grauacademico.py
capesbusca/filters/instituicao.py
capesbusca/filters/orientador.py
capesbusca/filters/programa.py
capesbusca/models/__init__.py
capesbusca/models/aggregate.py
capesbusca/models/aggregation.py
capesbusca/models/work.py