Metadata-Version: 2.1
Name: capesbusca
Version: 0.1.1
Summary: Biblioteca para realizar busca de termos no catálogo de teses e dissertações da Capes
Home-page: https://github.com/Vnicius/capes-busca
Author: Vinícius Veríssimo
Author-email: vinicius.matheus252@gmail.com
License: MIT
Download-URL: https://github.com/Vnicius/capes-busca/archive/v0.1.1.tar.gz
Keywords: data,api,capes,works
Platform: UNKNOWN
Classifier: Development Status :: 4 - Beta
Classifier: Intended Audience :: Developers
Classifier: Topic :: Software Development :: Build Tools
Classifier: License :: OSI Approved :: MIT License
Classifier: Programming Language :: Python :: 3
